{
  "title": "25 영업양도의 쟁점",
  "questions": [
    {
      "no": "01",
      "grade": "기",
      "theme": "대물적 허가와 인격변동",
      "q": "주류제조업면허는 제조장 단위의 이전성이 인정되는 소위 대물적 허가로서 허가받은 자의 인격변동이 당연히 허가취소사유에 해당하는 것은 아니다.",
      "ans": "O",
      "src": "11국회9",
      "exp": "주류제조업면허는 대물적 허가이므로 인격변동(양도 등)이 곧바로 허가취소사유가 되지 않는다는 것이 판례의 태도이다."
    },
    {
      "no": "02",
      "grade": "기",
      "theme": "제재사유의 승계",
      "q": "대물적 행정행위 중 수익적 행정행위인 경우에는 그 효과가 승계된다.",
      "ans": "O",
      "src": "12(하)지방9",
      "exp": "대물적 행정행위는 물적 상태에 착안한 것이므로 양도·양수 시 그 효과(지위)가 양수인에게 승계된다."
    },
    {
      "no": "03",
      "grade": "기",
      "theme": "제재처분사유 승계와 판단기준",
      "q": "사실상 영업이 양도·양수되었지만 아직 승계신고 및 수리처분이 있기 이전의 경우라면 행정제재 처분사유의 유무는 양도인을 기준으로 판단한다.",
      "ans": "O",
      "src": "19소방",
      "exp": "승계신고 수리 전에는 아직 양수인이 지위를 승계한 것이 아니므로 제재처분사유의 유무는 양도인을 기준으로 판단한다."
    },
    {
      "no": "04",
      "grade": "기",
      "theme": "영업자지위승계신고 수리 전 상대방",
      "q": "A구청장으로부터 허가를 받아 유흥주점영업을 해오던 甲이 해당 영업을 乙에게 양도하기로 하였다. 甲과 乙은 사업을 양도하기로 하는 계약을 체결하였고, 법령에 따라 乙은 A구청장에게 영업자지위승계신고를 하였다. A구청장이 영업자지위승계신고를 수리하기 전이라면 허가취소소처분의 상대방은 甲이다.",
      "ans": "O",
      "src": "23서울(지적)",
      "exp": "지위승계신고 수리 전에는 여전히 양도인 甲이 영업허가의 명의자이므로 허가취소처분의 상대방은 甲이다."
    },
    {
      "no": "05",
      "grade": "기",
      "theme": "승계신고 수리 전 위반행위 책임귀속",
      "q": "사실상 영업이 양도·양수되었지만 승계신고 및 그 수리처분이 있기 이전에 양도인이 양수인으로 하여금 영업을 하도록 허락하였다면 양수인의 영업 중 발생한 위반행위에 대한 행정적 책임은 양도인에게 귀속된다.",
      "ans": "O",
      "src": "25국가",
      "exp": "수리 전에는 양도인이 여전히 영업자 지위를 가지므로, 그 기간의 위반행위에 대한 행정적 책임은 양도인에게 귀속된다."
    },
    {
      "no": "06",
      "grade": "기",
      "theme": "양도인에 대한 제재사유의 양수인 승계",
      "q": "甲은 식품위생법상 식품접객업 영업허가를 받아 영업을 하던 중, 자신의 영업을 乙에게 양도하기로 계약을 체결하였고, 乙은 같은 법이 정한 바에 따라 영업자지위승계신고를 하였다. 관할행정청이 乙의 신고를 수리하기 전에 甲의 영업허가가 취소되었을 경우, 乙은 甲에 대한 영업허가취소에 대하여 취소소송을 제기할 수 있는 원고적격이 없다.",
      "ans": "X",
      "src": "15국9",
      "exp": "수리 전 양수인 乙은 양도인 甲에 대한 제재처분의 취소를 구할 법률상 이익(원고적격)이 인정된다는 것이 판례이다."
    },
    {
      "no": "07",
      "grade": "기",
      "theme": "주택건설사업 양도와 사업계획승인 취소통지",
      "q": "주택건설사업이 양도되었으나 그 변경승인을 받기 이전에 행정청이 양수인에 대하여 양도인에 대한 사업계획승인을 취소하였다는 사실을 통지한 경우 이러한 통지는 양수인의 법률적 지위에 변동을 일으키므로 행정처분이다.",
      "ans": "O",
      "src": "17서울",
      "exp": "양수인의 법적 지위에 변동을 초래하는 사업계획승인 취소통지는 항고소송의 대상이 되는 행정처분에 해당한다."
    },
    {
      "no": "08",
      "grade": "기",
      "theme": "제재사유 승계와 취소소송 법률상 이익",
      "q": "채석허가를 받은 자로부터 영업양도 후 명의변경신고 이전에 양도인의 법위반사유를 이유로 채석허가가 취소된 경우, 양도인의 지위를 승계한 양수인은 이러한 취소를 구할 법률상 이익을 가지지 않는다.",
      "ans": "X",
      "src": "17(하)국",
      "exp": "양수인은 양도인에 대한 채석허가 취소처분의 취소를 구할 법률상 이익을 가진다는 것이 판례의 태도이다."
    },
    {
      "no": "09",
      "grade": "기",
      "theme": "승계신고 수리 전 위반행위 제재 대상",
      "q": "甲은 식품위생법상 식품접객업 영업허가를 받아 영업을 하던 중 자신의 영업을 乙에게 양도하기로 계약을 체결하였고, 乙은 같은 법이 정한 바에 따라 영업자지위승계신고를 하였다. 관할행정청이 乙의 신고를 수리하기 전에 甲이 위반행위를 한 경우 그 제재처분의 상대방은 甲이다.",
      "ans": "O",
      "src": "15국",
      "exp": "수리 전 영업자 지위는 양도인 甲에게 있으므로 그 기간의 위반행위에 대한 제재처분의 상대방은 甲이다."
    },
    {
      "no": "10",
      "grade": "기",
      "theme": "영업양도 승계신고 수리의 처분성",
      "q": "식품위생법에 따른 영업양도에 따른 지위승계신고를 행정청이 수리하는 행위는 단순히 양도·양수인 사이에 이미 발생한 사법상의 사업양도의 법률효과에 의하여 양수인이 그 영업을 승계하였다는 사실의 신고를 접수하는 행위에 그치는 것이 아니라, 영업허가자의 변경이라는 법률효과를 발생시키는 행위이다.",
      "ans": "O",
      "src": "19지방",
      "exp": "영업양도에 따른 지위승계신고 수리는 영업허가자 변경이라는 법률효과를 발생시키는 처분(수리를 요하는 신고)이다."
    },
    {
      "no": "11",
      "grade": "기",
      "theme": "공매로 영업시설 인수와 신고수리 취소의 원고적격",
      "q": "공매 등의 절차로 영업시설의 전부를 인수함으로써 영업자의 지위를 승계한 자가 관계행정청에 이를 신고하여 행정청이 그 신고를 수리하는 처분에 대해 종전 영업자는 제3자로서 그 처분의 취소를 구할 법률상 이익이 인정되지 않는다.",
      "ans": "X",
      "src": "13국7",
      "exp": "공매로 지위를 승계당한 종전 영업자는 신고수리처분의 취소를 구할 법률상 이익(원고적격)이 인정된다."
    },
    {
      "no": "12",
      "grade": "기",
      "theme": "개인택시운송사업 양도·양수 인가의 성질",
      "q": "관할관청이 개인택시운송사업의 양도·양수에 대한 인가를 하였을 경우 거기에는 양도인과 양수인 간의 양도행위를 보충하여 그 법률효과를 완성시키는 의미에서의 인가처분뿐만 아니라 그 양도인이 가지고 있던 면허와 동일한 내용의 면허를 양수인에게 부여하는 처분이 포함되어 있다.",
      "ans": "O",
      "src": "20국회8",
      "exp": "개인택시 양도·양수 인가에는 보충적 인가처분과 함께 양수인에 대한 새로운 면허부여 처분이 포함되어 있다는 것이 판례이다."
    },
    {
      "no": "13",
      "grade": "S",
      "theme": "양도·양수계약 무효와 수리의 효력",
      "q": "甲이 乙에게 일반택시운송사업면허를 양도하고 乙과 양도·양수계약을 체결한 다음 관련법령에 따라 乙이 사업의 양도·양수신고를 한 경우, 甲과 乙 사이의 사업양도·양수계약이 무효이더라도 이에 대한 신고의 수리가 있게 되면 사업양도의 효과가 발생한다.",
      "ans": "X",
      "src": "17지방9",
      "exp": "기본행위인 양도·양수계약이 무효이면 그에 대한 수리가 있더라도 사업양도의 효과는 발생하지 않는다."
    },
    {
      "no": "14",
      "grade": "S",
      "theme": "양도·양수 무효와 신고수리 무효확인의 소",
      "q": "사업의 양도·양수신고가 수리된 경우, 甲은 민사쟁송으로 양도·양수행위의 무효를 구함이 없이 곧바로 항고소송으로 신고수리의 무효확인을 구할 법률상 이익이 있다.",
      "ans": "O",
      "src": "19지방",
      "exp": "기본행위의 무효를 이유로 곧바로 수리처분의 무효확인을 구할 법률상 이익이 인정된다는 것이 판례이다."
    },
    {
      "no": "19",
      "grade": "기",
      "theme": "대물적 영업양도와 양수인 제재",
      "q": "대물적 영업양도의 경우, 명시적인 규정이 없는 경우에도 양도 전에 존재하는 영업정지사유를 이유로 양수인에 대해서도 영업정지처분을 할 수 있다.",
      "ans": "O",
      "src": "13국7",
      "exp": "대물적 영업양도에서는 명문규정이 없어도 양도 전 제재사유를 이유로 양수인에게 영업정지처분을 할 수 있다."
    },
    {
      "no": "20",
      "grade": "기",
      "theme": "주유소허가 양수인의 지위 승계",
      "q": "주유소허가의 양수인은 양도인의 지위를 승계하므로 양도인에게 그 허가를 취소할 법적 사유가 있는 경우 이를 이유로 양수인에게 응분의 제재조치를 할 수 있다.",
      "ans": "O",
      "src": "19서울",
      "exp": "대물적 허가인 주유소허가의 양수인은 양도인의 지위를 승계하므로 양도인의 제재사유로 양수인을 제재할 수 있다."
    },
    {
      "no": "21",
      "grade": "기",
      "theme": "공중위생관리법상 지위승계와 영업정지사유",
      "q": "구 공중위생관리법에 따라 공중위생영업 양도·양수 후 양도인의 행정처분에 새로운 영업소개설통보를 하였던 양도인의 위법사유로 양수인에게 영업정지처분을 하는 것은 위법하다.",
      "ans": "X",
      "src": "25변",
      "exp": "공중위생영업 양수인은 양도인의 위반사유를 이유로 한 영업정지처분의 대상이 될 수 있으므로 이는 적법하다."
    },
    {
      "no": "22",
      "grade": "기",
      "theme": "영업양도 면적변경 신고 미이행과 제재",
      "q": "식품위생법에 따른 영업장 면적 변경에 관한 신고의무를 이행하지 않은 채 영업을 계속하는 경우, 시정명령 또는 영업정지 등 제재처분의 대상이 된다.",
      "ans": "O",
      "src": "25지방",
      "exp": "영업장 면적변경 신고의무를 이행하지 않고 영업을 계속하면 시정명령이나 영업정지 등 제재처분의 대상이 된다."
    },
    {
      "no": "23",
      "grade": "기",
      "theme": "운송사업 양도·양수 인가 후 양도인 사유로 취소",
      "q": "행정청은 개인택시 운송사업의 양도·양수에 대한 인가가 있은 후에도 그 양도·양수 이전에 있었던 양도인에 대한 운송사업면허 취소사유를 들어 양수인의 운송사업면허를 취소할 수 있다.",
      "ans": "O",
      "src": "14국",
      "exp": "양도·양수 인가 후에도 양도인에 대한 면허취소사유를 이유로 양수인의 운송사업면허를 취소할 수 있다."
    },
    {
      "no": "24",
      "grade": "기",
      "theme": "운송사업 양도·양수 시 취소사유 존재와 면허취소",
      "q": "행정청은 개인택시운송사업의 양도·양수 당시에 양도인에 대한 운송사업면허 취소사유가 현실적으로 발생하지 않았다면, 그 원인되는 사실이 존재하였더라도 그 후 발생한 운송사업면허 취소사유에 기하여 양수인의 사업면허를 취소할 수 없다.",
      "ans": "X",
      "src": "미기출",
      "exp": "양도·양수 당시 취소사유의 원인사실이 이미 존재하였다면, 그 후 취소사유가 발생하더라도 양수인의 면허를 취소할 수 있다."
    },
    {
      "no": "25",
      "grade": "기",
      "theme": "운전면허취소와 운송사업면허취소의 구별",
      "q": "양도인의 운전면허취소가 운송사업면허의 취소사유에 해당한다는 이유로 양수인의 운송사업면허를 취소하는 처분을 한 사안에서, 그 처분으로 인하여 공익상의 필요가 있다 하더라도 이로써 달성하려는 공익상의 필요보다 그 처분으로 양수인이 받게 되는 불이익이 훨씬 더 크다면 그 처분은 위법하게 된다.",
      "ans": "O",
      "src": "24군무",
      "exp": "운송사업면허취소는 비례원칙의 적용을 받으므로 침해되는 사익이 달성되는 공익보다 훨씬 크면 위법하다."
    },
    {
      "no": "26",
      "grade": "기",
      "theme": "제재처분 사유 있는 영업 양도 시 승계",
      "q": "행정처분에 의한 제재를 받을 사유가 있는 영업자가 영업을 양도하는 경우, 관련 규정에 양도인의 위반행위로 인한 제재를 양수인에게 승계할 수 있다는 명시적 규정이 없어도 그 제재의 효과가 양수인에게 승계된다.",
      "ans": "O",
      "src": "16국",
      "exp": "대물적 영업에서는 명시적 승계규정이 없더라도 양도인의 위반행위로 인한 제재의 효과가 양수인에게 승계된다."
    },
    {
      "no": "27",
      "grade": "A",
      "theme": "화물자동차운송사업 양수와 의무위반행위 승계",
      "q": "화물자동차법에 따라 운송사업을 양수하고 지위를 승계한 양수인이라 하더라도, 양도인의 의무위반행위로 인한 상태까지 승계하는 것이라고 볼 수는 없다.",
      "ans": "X",
      "src": "24국7",
      "exp": "운송사업 지위를 승계한 양수인은 양도인의 의무위반행위로 인한 법적 지위(제재사유)까지 승계한다."
    },
    {
      "no": "28",
      "grade": "A",
      "theme": "불법증차 사실 부지 양수인의 책임승계",
      "q": "양도인의 불법증차 사실을 모르고 운송사업을 양수한 경우, 양수인은 불법증차 차량에 대한 운송사업자로서의 책임을 승계하지 않는다.",
      "ans": "X",
      "src": "미기출",
      "exp": "불법증차 사실을 몰랐더라도 운송사업 양수인은 그에 관한 운송사업자로서의 책임을 승계한다는 것이 판례이다."
    },
    {
      "no": "29",
      "grade": "A",
      "theme": "불법증차 부정수급액의 양수인 반환",
      "q": "불법증차를 실행한 운송사업의 양수인에 대하여, 그 지위승계 전에 불법증차에 관하여 발생한 부정수급액에 대해서까지 양수인을 상대로 반환을 청구할 수는 없다.",
      "ans": "X",
      "src": "미기출",
      "exp": "양수인은 지위승계 전 불법증차 관련 부정수급액에 대해서도 반환의무를 승계한다는 것이 판례의 태도이다."
    },
    {
      "no": "30",
      "grade": "A",
      "theme": "유가보조금 반환명령의 성질",
      "q": "유가보조금 반환명령은 대물적 처분으로서, 대인적 처분인 운송사업 허가취소처분과 구별된다.",
      "ans": "O",
      "src": "미기출",
      "exp": "유가보조금 반환명령은 대물적 처분이고 운송사업 허가취소처분은 대인적 처분으로 서로 구별된다."
    },
    {
      "no": "31",
      "grade": "기",
      "theme": "회사분할과 제재사유 승계",
      "q": "합병 이전의 회사에 대한 분식회계를 이유로 감사인지정 및 손해배상공동기금의 추가적립의무를 명한 조치는 합병 후 존속하는 법인에게 승계될 수 있다.",
      "ans": "O",
      "src": "미기출",
      "exp": "분식회계를 이유로 한 감사인지정 및 추가적립의무 등의 제재조치는 합병 후 존속법인에 승계될 수 있다."
    },
    {
      "no": "32",
      "grade": "기",
      "theme": "회사분할과 제재사유의 신설회사 승계",
      "q": "회사분할 시 신설회사에 대하여 분할하는 회사의 분할 전 법 위반행위를 이유로 과징금을 부과하는 것은 허용되지 않는다.",
      "ans": "O",
      "src": "미기출",
      "exp": "회사분할 전 법 위반행위를 이유로 신설회사에 과징금을 부과하는 것은 허용되지 않는다는 것이 판례이다."
    },
    {
      "no": "33",
      "grade": "S",
      "theme": "회사분할과 제재사유의 승계",
      "q": "분할하는 회사의 분할 전 하도급거래 공정화에 관한 법 위반행위를 이유로 신설회사에 대하여 동법에 따른 시정조치나 과징금을 명하는 것이 허용된다.",
      "ans": "X",
      "src": "미기출",
      "exp": "분할 전 하도급법 위반행위를 이유로 신설회사에 시정조치나 과징금을 명하는 것은 원칙적으로 허용되지 않는다."
    },
    {
      "no": "34",
      "grade": "기",
      "theme": "하도급법상 벌점의 신설회사 승계",
      "q": "하도급법에 따른 벌점 부과는 단순 사실행위에 불과하므로, 분할 전 회사에 부과된 벌점이 분할신설회사에 승계된다고 볼 수 없다.",
      "ans": "X",
      "src": "미기출",
      "exp": "하도급법상 벌점은 분할신설회사에 승계된다는 것이 판례의 태도이므로 승계되지 않는다는 설명은 옳지 않다."
    },
    {
      "no": "35",
      "grade": "A",
      "theme": "요양기관 업무정지처분의 대물적 성질",
      "q": "요양기관이 속임수나 그 밖의 부당한 방법으로 보험자에게 요양급여비용을 부담하게 한 것을 이유로 국민건강보험법에 따라 받게 되는 요양기관 업무정지처분은 대물적 처분의 성격을 가진다.",
      "ans": "O",
      "src": "미기출",
      "exp": "요양기관 업무정지처분은 요양기관 자체에 대한 대물적 처분의 성격을 가진다는 것이 판례이다."
    },
    {
      "no": "36",
      "grade": "A",
      "theme": "업무정지처분 후 개설자 변경과 처분 가능",
      "q": "위반행위를 하여 업무정지처분의 대상이 된 요양기관이 폐업한 경우, 그 요양기관의 개설자가 새로 개설한 요양기관에 대하여 업무정지처분을 할 수 있다.",
      "ans": "X",
      "src": "미기출",
      "exp": "업무정지처분은 폐업한 요양기관에 대한 처분이므로 개설자가 새로 개설한 요양기관에 승계·집행할 수 없다."
    },
    {
      "no": "37",
      "grade": "기",
      "theme": "부정한 방법의 사업양수와 사업계획승인 취소",
      "q": "중간 사업시행자가 농업인 등이 아님에도 부정한 방법으로 사업계획승인을 취득하여 그 승인에 대한 취소사유가 있는 경우, 이를 들어 변경된 사업시행자에 대한 사업계획승인을 취소할 수 있다.",
      "ans": "O",
      "src": "미기출",
      "exp": "전 사업시행자의 부정한 방법으로 인한 승인 취소사유를 들어 변경된 사업시행자의 사업계획승인을 취소할 수 있다."
    }
  ]
}