{
  "title": "35 행정지도",
  "questions": [
    {
      "no": "01",
      "grade": "-",
      "theme": "의의·성질",
      "q": "행정지도는 행정목적 달성에 필요한 제재를 가하기 위하여 행하여지는 단계적 행정행위로서의 사전적인 행위라 볼 수 있다.",
      "ans": "X",
      "src": "08(상)지방9",
      "exp": "행정지도는 제재나 행정행위가 아니라 비권력적 사실행위이다."
    },
    {
      "no": "02",
      "grade": "기",
      "theme": "의의·성질",
      "q": "행정지도란 행정기관이 그 소관 사무의 범위에서 일정한 행정목적을 실현하기 위하여 특정인에게 일정한 행위를 하거나 하지 아니하도록 지도, 권고, 조언 등을 하는 행정작용을 말한다.",
      "ans": "O",
      "src": "21소방",
      "exp": "행정절차법 제2조의 행정지도 정의로 옳다."
    },
    {
      "no": "03",
      "grade": "기",
      "theme": "의의·성질",
      "q": "행정지도는 사실상 강제력으로 인하여 권력적 행정활동이 원칙이다.",
      "ans": "X",
      "src": "11지방9",
      "exp": "행정지도는 비권력적 사실행위가 원칙이다."
    },
    {
      "no": "04",
      "grade": "-",
      "theme": "의의·성질",
      "q": "행정지도는 법적 효과의 발생을 목적으로 하는 의사표시이다.",
      "ans": "X",
      "src": "18교행9",
      "exp": "행정지도는 법적 효과의 발생을 목적으로 하지 않는 비권력적 사실행위이다."
    },
    {
      "no": "05",
      "grade": "C",
      "theme": "법적 근거",
      "q": "다수설에 따르면 행정지도에 관해서 개별법에 근거규정이 없는 경우 행정지도의 상대방인 국민에게 미치는 효과를 고려하여 행정지도를 할 수 없다고 본다.",
      "ans": "X",
      "src": "17(상)국가9",
      "exp": "다수설은 비권력적 행정지도는 개별 작용법적 근거가 없어도 조직법적 근거만 있으면 할 수 있다고 본다."
    },
    {
      "no": "06",
      "grade": "소",
      "theme": "법적 근거",
      "q": "행정지도 중 규제적·구속적 행정지도의 경우에는 법적 근거가 필요하다는 견해가 있다.",
      "ans": "O",
      "src": "21소방",
      "exp": "규제적·구속적 행정지도에는 법적 근거가 필요하다는 견해가 있다."
    },
    {
      "no": "07",
      "grade": "Z",
      "theme": "종류",
      "q": "영농지도, 중소기업에 대한 경영지도, 생활개선지도는 조성적 행정지도에 해당한다.",
      "ans": "O",
      "src": "12국가9",
      "exp": "이들은 조성적 행정지도의 예이다."
    },
    {
      "no": "08",
      "grade": "-",
      "theme": "한계",
      "q": "행정지도는 비권력적 사실행위이므로 당해 행정기관 소관 사무의 범위를 벗어나는 경우에도 허용된다.",
      "ans": "X",
      "src": "20소간",
      "exp": "행정지도는 소관 사무의 범위 내에서만 허용된다(행정절차법 제48조)."
    },
    {
      "no": "09",
      "grade": "C",
      "theme": "행정절차법",
      "q": "행정지도는 의무를 부과하거나 권익을 제한하는 것이 아니므로「행정절차법」의 적용을 받지 않는다.",
      "ans": "X",
      "src": "23국회8",
      "exp": "행정지도는 의무부과·권익제한이 아니며, 행정절차법에 행정지도에 관한 규정이 있어 그 적용을 받는다."
    },
    {
      "no": "10",
      "grade": "기",
      "theme": "한계",
      "q": "행정지도는 작용법적 근거가 필요하지 않으므로, 비례원칙과 평등원칙에 구속되지 않는다.",
      "ans": "X",
      "src": "19국가9",
      "exp": "행정지도도 비례원칙·평등원칙 등 행정법의 일반원칙에 구속된다."
    },
    {
      "no": "11",
      "grade": "C",
      "theme": "한계",
      "q": "행정지도를 함에 있어서 명문의 규정은 없더라도 비례원칙이 적용된다.",
      "ans": "X",
      "src": "12국가7",
      "exp": "비례원칙은 행정절차법 제48조 제1항('행정지도는 그 목적 달성에 필요한 최소한도에 그쳐야 하며')에 명문으로 규정되어 있다. '명문의 규정은 없지만'이라는 부분이 틀렸다."
    },
    {
      "no": "12",
      "grade": "C",
      "theme": "한계",
      "q": "행정지도는 그 목적달성에 필요한 최소한도에 그쳐야 한다.",
      "ans": "O",
      "src": "20소방",
      "exp": "행정절차법 제48조 제1항의 과잉금지(비례)원칙이다."
    },
    {
      "no": "13",
      "grade": "C",
      "theme": "한계",
      "q": "상대방의 의사에 반하여 부당하게 강요하는 행정지도는 위법하다.",
      "ans": "O",
      "src": "23지방9",
      "exp": "행정절차법 제48조 제1항 위반으로 위법하다."
    },
    {
      "no": "14",
      "grade": "C",
      "theme": "행정절차법",
      "q": "「행정절차법」에 따르면, 행정기관은 행정지도의 상대방이 행정지도에 따르지 않았다는 것을 이유로 불이익한 조치를 하여서는 아니 된다고 규정하고 있다.",
      "ans": "O",
      "src": "13지방9",
      "exp": "행정절차법 제48조 제2항 불이익조치 금지 규정이다."
    },
    {
      "no": "15",
      "grade": "-",
      "theme": "한계",
      "q": "행정지도의 상대방이 행정지도에 따르지 않았다고 하여 불이익한 조치를 하는 것은 법리적으로 비례의 원칙에 어긋나는 과잉지도로 볼 수 있다.",
      "ans": "X",
      "src": "08(상)지방9",
      "exp": "행정지도에 따르지 않았다는 이유로 불이익한 조치를 하는 것은 행정절차법 제48조 제2항의 불이익조치 금지(임의성 원칙) 위반의 문제이지, 비례원칙에 어긋나는 과잉지도의 문제가 아니다."
    },
    {
      "no": "16",
      "grade": "소",
      "theme": "절차",
      "q": "행정지도를 하는 자는 그 상대방에게 그 행정지도의 취지 및 내용을 밝혀야 하지만 신분은 생략할 수 있다.",
      "ans": "X",
      "src": "20소방",
      "exp": "행정절차법 제49조 제1항상 취지·내용은 물론 신분도 밝혀야 한다."
    },
    {
      "no": "17",
      "grade": "B",
      "theme": "절차",
      "q": "행정지도의 상대방은 행정지도의 내용에 동의하지 않는 경우 이를 따르지 않을 수 있으므로, 행정지도의 내용이나 방식에 대해 의견제출권을 갖지 않는다.",
      "ans": "X",
      "src": "17(상)국가9",
      "exp": "행정절차법 제50조상 상대방은 행정지도의 내용·방식에 관하여 의견제출권을 가진다."
    },
    {
      "no": "18",
      "grade": "B",
      "theme": "절차",
      "q": "「행정절차법」에 따르면 행정지도의 상대방은 해당 행정지도의 내용에 관하여서뿐만 아니라 그 방식에 관하여도 행정기관에 의견을 제출할 수 있다.",
      "ans": "O",
      "src": "17국회8",
      "exp": "행정절차법 제50조의 의견제출 규정이다."
    },
    {
      "no": "19",
      "grade": "C",
      "theme": "절차",
      "q": "행정지도가 다수인을 대상으로 할 경우에도 명령·강제작용이 아니기 때문에「행정절차법」은 특별한 사정이 없으면 공표할 필요가 없다고 규정한다.",
      "ans": "X",
      "src": "11지방9",
      "exp": "행정절차법 제51조상 다수인을 대상으로 하는 경우 특별한 사정이 없으면 공통되는 사항을 공표하여야 한다."
    },
    {
      "no": "20",
      "grade": "B",
      "theme": "절차",
      "q": "「행정절차법」은 행정지도는 반드시 서면으로 하여야 하고 그 서면에는 행정지도의 취지·내용을 기재하도록 규정함으로써 행정지도의 명확성을 요구하고 있다.",
      "ans": "X",
      "src": "17국회8",
      "exp": "행정지도는 말로도 할 수 있으며, 상대방이 서면 교부를 요구하면 교부하면 된다(제49조 제2항)."
    },
    {
      "no": "N1",
      "grade": "-",
      "theme": "의의·성질",
      "q": "밑줄 친 부분의 행정작용에 해당하는 것은?\n\n[정부는 다음 달 초부터 자동차 운전자들이 자주 일삼는 교차로 꼬리물기에 대하여 단속보다는 이를 지양하는 방향으로 '계도하기'로 하고 적극 홍보에 나섰다.]\n\n① 행정기관이 장래 일정기간 내에 도달해야 할 목표를 설정하고 제 수단을 조정·통합하는 작용 또는 그 활동기준\n② 행정기관이 행정목적을 실현하기 위하여 특정인에게 일정한 행위를 하거나 하지 아니하도록 지도·권고·조언 등을 하는 행정작용\n③ 행정활동의 한 수단으로 공행정 목적을 수행하기 위한 계약적 행정작용\n④ 일정한 행정작용을 하거나 하지 않을 것을 내용으로 하는 행정청의 구속력 있는 약속",
      "ans": "②",
      "src": "11사복9",
      "exp": "밑줄 친 '계도'는 행정지도에 해당하며, ②가 행정지도의 정의이다(행정절차법 제2조 제3호). ①은 행정계획, ③은 공법상 계약, ④는 확약에 대한 설명이다."
    },
    {
      "no": "21",
      "grade": "B",
      "theme": "처분성",
      "q": "지도, 권고, 조언 등의 행정지도는 법령의 근거를 요하고 항고소송의 대상이 된다.",
      "ans": "X",
      "src": "17국가9",
      "exp": "단순한 지도·권고·조언은 비권력적 사실행위로서 항고소송의 대상이 되는 처분이 아니다."
    },
    {
      "no": "22",
      "grade": "B",
      "theme": "처분성",
      "q": "판례에 따르면 세무당국이 주류거래를 일정 기간 중지하여 줄 것을 요청한 행위는 항고소송의 대상이다.",
      "ans": "X",
      "src": "16교행9",
      "exp": "주류거래 중지 요청은 행정지도에 불과하여 항고소송의 대상이 되는 처분이 아니다."
    },
    {
      "no": "23",
      "grade": "인",
      "theme": "헌법소원",
      "q": "노동부장관이 공공기관 단체협약내용을 분석하여 불합리한 요소를 개선하라고 요구한 행위는 행정지도로서의 한계를 넘어 규제적·구속적 성격을 강하게 갖는다고 할 수 없어 헌법소원의 대상이 되는 공권력의 행사에 해당한다고 볼 수 없다.",
      "ans": "O",
      "src": "17(하)지방9",
      "exp": "해당 개선요구는 규제적·구속적 성격이 강하지 않아 공권력 행사에 해당하지 않는다."
    },
    {
      "no": "24",
      "grade": "C",
      "theme": "헌법소원",
      "q": "행정기관의 조언에 따르지 않을 경우 일정한 불이익조치가 예정되어 있어 사실상 상대방에게 그에 따를 의무를 부과하는 것과 다를 바 없더라도 그 조언이 행정지도에 불과한 이상 이는「헌법재판소법」제68조 제1항의 헌법소원심판의 대상이 되는 공권력의 행사라 할 수 없다.",
      "ans": "X",
      "src": "21변시",
      "exp": "조언에 따르지 않을 경우 일정한 불이익조치가 예정되어 있어 사실상 상대방에게 그에 따를 의무를 부과하는 것과 다를 바 없는 경우에는, 행정지도의 한계를 넘어 규제적·구속적 성격을 갖는 것으로서 헌법소원심판의 대상이 되는 공권력의 행사에 해당할 수 있다."
    },
    {
      "no": "25",
      "grade": "C",
      "theme": "헌법소원",
      "q": "행정지도는 비권력적 사실행위이므로 행정지도가 그 한계를 넘어 규제적·구속적 성격을 강하게 갖는 경우라 하여 헌법소원의 대상이 되는 공권력의 행사에 해당한다고 볼 수는 없다.",
      "ans": "X",
      "src": "17국회8",
      "exp": "규제적·구속적 성격을 강하게 갖는 경우에는 예외적으로 헌법소원의 대상이 되는 공권력 행사에 해당할 수 있다."
    },
    {
      "no": "26",
      "grade": "B",
      "theme": "헌법소원",
      "q": "교육인적자원부장관의 (구)공립대학들에 대한 학칙시정요구는 고등교육법령에 따른 것으로 그 법적 성격은 임의적 협력을 통한 사실상의 효과를 발생시키는 행정지도의 일종으로 헌법소원의 대상이 되는 공권력의 행사로 볼 수 없다.",
      "ans": "X",
      "src": "21소방",
      "exp": "학칙시정요구는 규제적·구속적 성격이 강하여 헌법소원의 대상이 되는 공권력의 행사에 해당한다."
    },
    {
      "no": "27",
      "grade": "-",
      "theme": "헌법소원",
      "q": "금융위원회위원장이 시중 은행을 상대로 투기지역·투기과열지구 내 초고가 아파트에 대한 주택구입용 주택담보대출을 금지한 조치는 규제적·구속적 성격을 갖는 행정지도로서 헌법소원의 대상이 되는 공권력 행사에 해당된다.",
      "ans": "O",
      "src": "25변시",
      "exp": "헌법재판소는 금융위원회위원장의 초고가 아파트에 대한 주택구입용 주택담보대출 금지 조치를 단순한 행정지도의 한계를 넘은 규제적·구속적 성격을 갖는 행정지도로서 헌법소원의 대상이 되는 공권력의 행사에 해당한다고 보았다."
    },
    {
      "no": "28",
      "grade": "B",
      "theme": "손해배상",
      "q": "행정지도가 강제성을 띠지 않은 비권력적 작용으로서 지도의 한계를 일탈하지 아니하였다 하더라도 그로 인하여 상대방에게 어떤 손해가 발생하였다면 행정기관은 그에 대한 손해배상책임을 진다.",
      "ans": "X",
      "src": "14(1)경행",
      "exp": "한계를 일탈하지 않은 적법한 행정지도로 인한 손해에 대해서는 손해배상책임을 지지 않는다(위법성·인과관계 부정)."
    },
    {
      "no": "29",
      "grade": "B",
      "theme": "손해배상",
      "q": "행정지도의 한계일탈로 인해 상대방에게 손해가 발생한 경우 행정기관은 손해배상책임이 없다.",
      "ans": "X",
      "src": "18(1)서울7",
      "exp": "한계를 일탈한 위법한 행정지도로 손해가 발생하면 손해배상책임을 진다."
    },
    {
      "no": "30",
      "grade": "-",
      "theme": "손해배상",
      "q": "위법한 행정지도로 손해가 발생한 경우 국가 등을 상대로 손해배상을 청구할 수 있으나, 이 경우「국가배상법」제2조가 정한 배상책임의 요건을 갖추어야 한다.",
      "ans": "O",
      "src": "18(1)서울7",
      "exp": "국가배상 청구를 위해서는 국가배상법 제2조의 요건을 갖추어야 한다."
    },
    {
      "no": "31",
      "grade": "인",
      "theme": "손해배상",
      "q": "행정기관의 위법한 행정지도로 일정 기간 어업권을 행사하지 못하는 손해를 입은 자가 그 어업권을 타인에게 매도하여 매매대금 상당의 이득을 얻은 경우, 손해배상액의 산정에서 그 이득을 손익상계할 수 있다.",
      "ans": "X",
      "src": "17(하)지방9",
      "exp": "해당 이득은 손해배상액 산정에서 손익상계의 대상이 되지 않는다."
    },
    {
      "no": "32",
      "grade": "B",
      "theme": "위법성",
      "q": "위법한 행정지도에 따라 행한 사인의 행위는 법령에 명시적으로 정함이 없는 한 위법성이 조각된다고 할 수 없다.",
      "ans": "O",
      "src": "17(상)국가9",
      "exp": "위법한 행정지도에 따른 사인의 행위라도 명문 규정이 없는 한 위법성이 조각되지 않는다."
    },
    {
      "no": "33",
      "grade": "B",
      "theme": "위법성",
      "q": "행정관청이 구「국토이용관리법」소정의 토지거래계약신고에 관하여 공시된 기준시가를 기준으로 매매가격을 신고하도록 행정지도를 하여 그에 따라 허위신고를 한 것이라 하더라도 이와 같은 행정지도는 법에 어긋나는 것으로서 그 범법행위가 정당화될 수 없다.",
      "ans": "O",
      "src": "17(하)지방9",
      "exp": "위법한 행정지도에 따른 허위신고는 정당화되지 않는다."
    },
    {
      "no": "34",
      "grade": "-",
      "theme": "위법성",
      "q": "재무부장관이 대통령의 지시에 따라 정해진 정부의 방침을 행정지도라는 방법으로 금융기관에 전달함에 있어 통상의 행정지도와는 달리 사실상 지시하는 방법으로 행한 경우에는 헌법상의 법치주의원리, 시장경제의 원리에 반한다.",
      "ans": "O",
      "src": "10국회8",
      "exp": "사실상 지시에 해당하는 관치금융은 법치주의·시장경제 원리에 반한다."
    },
    {
      "no": "35",
      "grade": "Z",
      "theme": "위법성",
      "q": "구 재무부의 주거래은행에 대한 행정지도(매각권유의 지시)가 위헌이라면, 주거래 은행의 권유로 매각조건에 관한 오랜 협상을 통해 주식매매계약이 성립되었다고 하더라도 구 재무부의 행정지도는 강박이 되고 당해 주식매매계약은 무효이다.",
      "ans": "X",
      "src": "20소간",
      "exp": "오랜 협상을 거쳐 성립한 매매계약에서 그 행정지도가 강박에 해당한다거나 계약이 무효가 되는 것은 아니다."
    },
    {
      "no": "36",
      "grade": "-",
      "theme": "위법성",
      "q": "적법한 행정지도로 인정되기 위해서는 그 목적이 적법한 것으로 인정될 수 있어야 하므로, 행정청이 행한 주식매각의 종용이 정당한 법률적 근거 없이 자의적으로 주주에게 제재를 가하는 것이라면 행정지도의 영역을 벗어난 것이라고 보아야 한다.",
      "ans": "O",
      "src": "20군무원9",
      "exp": "정당한 근거 없이 자의적 제재를 가하는 종용은 행정지도의 한계를 벗어난 것이다."
    }
  ]
}